{
  "agregar": [
    {
      "codigoFormato": "1",
      "correlativo": "1",
      "descripcion": "header",
      "valorTipoDatos": "CONSTANTE",
      "constante": "{\"datos\":\"",
      "removerCeros": false,
      "mascaraImpresion": "",
      "valorEspecificacionCaracteristica1": "",
      "valorOperador": "",
      "valorEspecificaciOnCaracteristica2": "",
      "leerPosInicial": "1",
      "leerTamDatos": "1",
      "imprimirFila": "1",
      "imprimirTamDatos": "2",
      "imprimirPosicionColumna": "",
      "expresionDatosRecurso": "",
      "expresion1": "",
      "valorOperacion": "",
      "expresion2": "",
      "valorTipoExpresion": ""
    }

    ]
}