{
  "agregar": [
    {
      "codigo": 1,
      "arbolRaiz": "Byte S.A.",
      "nombre": "Efectivo en caja",
      "nombreCorto": "Efectivo en caja",
      "descripcion": "",
      "validaMontos": "true",
      "minimoRequiereAutorizacion": "true",
      "maximoRequiereAutorizacion": "true",
      "correlativoImpreso": 1,
      "enviarHost": "",
      "cicloVida": "Activo",
      "validoDesde": "01/02/26",
      "validoHasta": "",
      "totalMonitoreado": "true",
      "rutinaCalculamontoConciliar": "",
      "rutinacalculaMontoConciliado": "",
      "esControlEfectivo": "Efectivo Físico"
    },
    {
      "codigo": 2,
      "arbolRaiz": "Byte S.A.",
      "nombre": "Efectivo recibido",
      "nombreCorto": "Efectivo recibido",
      "descripcion": "",
      "validaMontos": "",
      "minimoRequiereAutorizacion": "",
      "maximoRequiereAutorizacion": "",
      "correlativoImpreso": 2,
      "enviarHost": "",
      "cicloVida": "Activo",
      "validoDesde": "01/02/26",
      "validoHasta": "",
      "totalMonitoreado": "",
      "rutinaCalculamontoConciliar": "",
      "rutinacalculaMontoConciliado": "",
      "esControlEfectivo": "No Aplica"
    },
    {
      "codigo": 6,
      "arbolRaiz": "Byte S.A.",
      "nombre": "Recibido del publico",
      "nombreCorto": "Recibido del publi",
      "descripcion": "",
      "validaMontos": "",
      "minimoRequiereAutorizacion": "",
      "maximoRequiereAutorizacion": "",
      "correlativoImpreso": 6,
      "enviarHost": "",
      "cicloVida": "Lanzado",
      "validoDesde": "01/02/26",
      "validoHasta": "",
      "totalMonitoreado": "",
      "rutinaCalculamontoConciliar": "",
      "rutinacalculaMontoConciliado": "",
      "esControlEfectivo": "No Aplica"
    },
    {
      "codigo": 20,
      "arbolRaiz": "Byte S.A.",
      "nombre": "Efectivo entregado",
      "nombreCorto": "Efectivo entregado",
      "descripcion": "",
      "validaMontos": "",
      "minimoRequiereAutorizacion": "",
      "maximoRequiereAutorizacion": "",
      "correlativoImpreso": 20,
      "enviarHost": "",
      "cicloVida": "Activo",
      "validoDesde": "01/02/26",
      "validoHasta": "",
      "totalMonitoreado": "",
      "rutinaCalculamontoConciliar": "",
      "rutinacalculaMontoConciliado": "",
      "esControlEfectivo": "No Aplica"
    },
    {
      "codigo": 21,
      "arbolRaiz": "Byte S.A.",
      "nombre": "Entregado al público",
      "nombreCorto": "Entregado al públi",
      "descripcion": "",
      "validaMontos": "",
      "minimoRequiereAutorizacion": "",
      "maximoRequiereAutorizacion": "",
      "correlativoImpreso": 21,
      "enviarHost": "",
      "cicloVida": "Activo",
      "validoDesde": "01/02/26",
      "validoHasta": "",
      "totalMonitoreado": "",
      "rutinaCalculamontoConciliar": "",
      "rutinacalculaMontoConciliado": "",
      "esControlEfectivo": "No Aplica"
    },
    {
      "codigo": 40,
      "arbolRaiz": "Byte S.A.",
      "nombre": "Efectivo electrónico",
      "nombreCorto": "Efvo electronico",
      "descripcion": "",
      "validaMontos": "",
      "minimoRequiereAutorizacion": "",
      "maximoRequiereAutorizacion": "",
      "correlativoImpreso": 40,
      "enviarHost": "",
      "cicloVida": "Activo",
      "validoDesde": "01/02/26",
      "validoHasta": "",
      "totalMonitoreado": "true",
      "rutinaCalculamontoConciliar": "",
      "rutinacalculaMontoConciliado": "",
      "esControlEfectivo": "Efectivo electrónico"
    },
    {
      "codigo": 41,
      "arbolRaiz": "Byte S.A.",
      "nombre": "Efectivo electronico recibido",
      "nombreCorto": "Efectivo electronic",
      "descripcion": "",
      "validaMontos": "",
      "minimoRequiereAutorizacion": "",
      "maximoRequiereAutorizacion": "",
      "correlativoImpreso": 41,
      "enviarHost": "",
      "cicloVida": "Activo",
      "validoDesde": "01/02/26",
      "validoHasta": "",
      "totalMonitoreado": "",
      "rutinaCalculamontoConciliar": "",
      "rutinacalculaMontoConciliado": "",
      "esControlEfectivo": "No Aplica"
    },
    {
      "codigo": 42,
      "arbolRaiz": "Byte S.A.",
      "nombre": "Efectivo electrónico pagado",
      "nombreCorto": "Efectivo electronic",
      "descripcion": "",
      "validaMontos": "",
      "minimoRequiereAutorizacion": "",
      "maximoRequiereAutorizacion": "",
      "correlativoImpreso": 42,
      "enviarHost": "",
      "cicloVida": "Activo",
      "validoDesde": "01/02/26",
      "validoHasta": "",
      "totalMonitoreado": "",
      "rutinaCalculamontoConciliar": "",
      "rutinacalculaMontoConciliado": "",
      "esControlEfectivo": "No Aplica"
    },
    {
      "codigo": 50,
      "arbolRaiz": "Byte S.A.",
      "nombre": "Documentos recibidos",
      "nombreCorto": "Documentos recibidos",
      "descripcion": "",
      "validaMontos": "",
      "minimoRequiereAutorizacion": "",
      "maximoRequiereAutorizacion": "",
      "correlativoImpreso": 50,
      "enviarHost": "",
      "cicloVida": "Activo",
      "validoDesde": "01/02/26",
      "validoHasta": "",
      "totalMonitoreado": "",
      "rutinaCalculamontoConciliar": "",
      "rutinacalculaMontoConciliado": "",
      "esControlEfectivo": "No Aplica"
    },
    {
      "codigo": 51,
      "arbolRaiz": "Byte S.A.",
      "nombre": "Cheques propios pagados",
      "nombreCorto": "Cheques propios pag",
      "descripcion": "",
      "validaMontos": "",
      "minimoRequiereAutorizacion": "",
      "maximoRequiereAutorizacion": "",
      "correlativoImpreso": 51,
      "enviarHost": "",
      "cicloVida": "Activo",
      "validoDesde": "01/02/26",
      "validoHasta": "",
      "totalMonitoreado": "",
      "rutinaCalculamontoConciliar": "",
      "rutinacalculaMontoConciliado": "",
      "esControlEfectivo": "No Aplica"
    },
    {
      "codigo": 52,
      "arbolRaiz": "Byte S.A.",
      "nombre": "Cheques propios pagados en caja",
      "nombreCorto": "Cheques propios pa",
      "descripcion": "",
      "validaMontos": "",
      "minimoRequiereAutorizacion": "",
      "maximoRequiereAutorizacion": "",
      "correlativoImpreso": 52,
      "enviarHost": "",
      "cicloVida": "Activo",
      "validoDesde": "01/02/26",
      "validoHasta": "",
      "totalMonitoreado": "",
      "rutinaCalculamontoConciliar": "",
      "rutinacalculaMontoConciliado": "",
      "esControlEfectivo": "No Aplica"
    },
    {
      "codigo": 70,
      "arbolRaiz": "Byte S.A.",
      "nombre": "Cheques de otros bancos",
      "nombreCorto": "Cheques de otros ba",
      "descripcion": "",
      "validaMontos": "",
      "minimoRequiereAutorizacion": "",
      "maximoRequiereAutorizacion": "",
      "correlativoImpreso": 70,
      "enviarHost": "",
      "cicloVida": "Activo",
      "validoDesde": "01/02/26",
      "validoHasta": "",
      "totalMonitoreado": "",
      "rutinaCalculamontoConciliar": "",
      "rutinacalculaMontoConciliado": "",
      "esControlEfectivo": "No Aplica"
    },
    {
      "codigo": 71,
      "arbolRaiz": "Byte S.A.",
      "nombre": "Cheques ob recibos en depósito",
      "nombreCorto": "Cheques ob recibos",
      "descripcion": "",
      "validaMontos": "",
      "minimoRequiereAutorizacion": "",
      "maximoRequiereAutorizacion": "",
      "correlativoImpreso": 71,
      "enviarHost": "",
      "cicloVida": "Activo",
      "validoDesde": "01/02/26",
      "validoHasta": "",
      "totalMonitoreado": "",
      "rutinaCalculamontoConciliar": "",
      "rutinacalculaMontoConciliado": "",
      "esControlEfectivo": "No Aplica"
    },
    {
      "codigo": 80,
      "arbolRaiz": "Byte S.A.",
      "nombre": "Giros del exterior",
      "nombreCorto": "Giros del exterior",
      "descripcion": "",
      "validaMontos": "",
      "minimoRequiereAutorizacion": "",
      "maximoRequiereAutorizacion": "",
      "correlativoImpreso": 80,
      "enviarHost": "",
      "cicloVida": "Activo",
      "validoDesde": "01/02/26",
      "validoHasta": "",
      "totalMonitoreado": "",
      "rutinaCalculamontoConciliar": "",
      "rutinacalculaMontoConciliado": "",
      "esControlEfectivo": "No Aplica"
    },
    {
      "codigo": 81,
      "arbolRaiz": "Byte S.A.",
      "nombre": "Giros exterior recibidos en depósito",
      "nombreCorto": "Giros exterior rec",
      "descripcion": "",
      "validaMontos": "",
      "minimoRequiereAutorizacion": "",
      "maximoRequiereAutorizacion": "",
      "correlativoImpreso": 81,
      "enviarHost": "",
      "cicloVida": "Activo",
      "validoDesde": "01/02/26",
      "validoHasta": "",
      "totalMonitoreado": "",
      "rutinaCalculamontoConciliar": "",
      "rutinacalculaMontoConciliado": "",
      "esControlEfectivo": "No Aplica"
    },
    {
      "codigo": 100,
      "arbolRaiz": "Byte S.A.",
      "nombre": "Creditos",
      "nombreCorto": "Creditos",
      "descripcion": "",
      "validaMontos": "",
      "minimoRequiereAutorizacion": "",
      "maximoRequiereAutorizacion": "",
      "correlativoImpreso": 100,
      "enviarHost": "",
      "cicloVida": "Activo",
      "validoDesde": "01/02/26",
      "validoHasta": "",
      "totalMonitoreado": "",
      "rutinaCalculamontoConciliar": "",
      "rutinacalculaMontoConciliado": "",
      "esControlEfectivo": "No Aplica"
    },
    {
      "codigo": 101,
      "arbolRaiz": "Byte S.A.",
      "nombre": "101Monetarios",
      "nombreCorto": "101Monetarios",
      "descripcion": "",
      "validaMontos": "",
      "minimoRequiereAutorizacion": "",
      "maximoRequiereAutorizacion": "",
      "correlativoImpreso": 101,
      "enviarHost": "",
      "cicloVida": "Activo",
      "validoDesde": "01/02/26",
      "validoHasta": "",
      "totalMonitoreado": "",
      "rutinaCalculamontoConciliar": "",
      "rutinacalculaMontoConciliado": "",
      "esControlEfectivo": "No Aplica"
    },
    {
      "codigo": 102,
      "arbolRaiz": "Byte S.A.",
      "nombre": "Depositos monetarios",
      "nombreCorto": "Depositos monetari",
      "descripcion": "",
      "validaMontos": "",
      "minimoRequiereAutorizacion": "",
      "maximoRequiereAutorizacion": "",
      "correlativoImpreso": 102,
      "enviarHost": "",
      "cicloVida": "Activo",
      "validoDesde": "01/02/26",
      "validoHasta": "",
      "totalMonitoreado": "true",
      "rutinaCalculamontoConciliar": "",
      "rutinacalculaMontoConciliado": "",
      "esControlEfectivo": "No Aplica"
    },
    {
      "codigo": 140,
      "arbolRaiz": "Byte S.A.",
      "nombre": "140Ahorros",
      "nombreCorto": "140Ahorros",
      "descripcion": "",
      "validaMontos": "",
      "minimoRequiereAutorizacion": "",
      "maximoRequiereAutorizacion": "",
      "correlativoImpreso": 140,
      "enviarHost": "",
      "cicloVida": "Activo",
      "validoDesde": "01/02/26",
      "validoHasta": "",
      "totalMonitoreado": "true",
      "rutinaCalculamontoConciliar": "",
      "rutinacalculaMontoConciliado": "",
      "esControlEfectivo": "No Aplica"
    },
    {
      "codigo": 141,
      "arbolRaiz": "Byte S.A.",
      "nombre": "Depositos de ahorro",
      "nombreCorto": "Depositos de ahorr",
      "descripcion": "",
      "validaMontos": "",
      "minimoRequiereAutorizacion": "",
      "maximoRequiereAutorizacion": "",
      "correlativoImpreso": 141,
      "enviarHost": "",
      "cicloVida": "Activo",
      "validoDesde": "01/02/26",
      "validoHasta": "",
      "totalMonitoreado": "",
      "rutinaCalculamontoConciliar": "",
      "rutinacalculaMontoConciliado": "",
      "esControlEfectivo": "No Aplica"
    },
    {
      "codigo": 142,
      "arbolRaiz": "Byte S.A.",
      "nombre": "Depositos de ahorro con libreta",
      "nombreCorto": "Depositos de ahor",
      "descripcion": "",
      "validaMontos": "",
      "minimoRequiereAutorizacion": "",
      "maximoRequiereAutorizacion": "",
      "correlativoImpreso": 142,
      "enviarHost": "",
      "cicloVida": "Activo",
      "validoDesde": "01/02/26",
      "validoHasta": "",
      "totalMonitoreado": "true",
      "rutinaCalculamontoConciliar": "",
      "rutinacalculaMontoConciliado": "",
      "esControlEfectivo": "No Aplica"
    },
    {
      "codigo": 143,
      "arbolRaiz": "Byte S.A.",
      "nombre": "Depositos de ahorro sin libreta",
      "nombreCorto": "Depositos de ahor",
      "descripcion": "",
      "validaMontos": "",
      "minimoRequiereAutorizacion": "",
      "maximoRequiereAutorizacion": "",
      "correlativoImpreso": 143,
      "enviarHost": "",
      "cicloVida": "Activo",
      "validoDesde": "01/02/26",
      "validoHasta": "",
      "totalMonitoreado": "true",
      "rutinaCalculamontoConciliar": "",
      "rutinacalculaMontoConciliado": "",
      "esControlEfectivo": "No Aplica"
    },
    {
      "codigo": 300,
      "arbolRaiz": "Byte S.A.",
      "nombre": "Débitos",
      "nombreCorto": "Débitos",
      "descripcion": "",
      "validaMontos": "",
      "minimoRequiereAutorizacion": "",
      "maximoRequiereAutorizacion": "",
      "correlativoImpreso": 300,
      "enviarHost": "",
      "cicloVida": "Activo",
      "validoDesde": "01/02/26",
      "validoHasta": "",
      "totalMonitoreado": "",
      "rutinaCalculamontoConciliar": "",
      "rutinacalculaMontoConciliado": "",
      "esControlEfectivo": "No Aplica"
    },
    {
      "codigo": 301,
      "arbolRaiz": "Byte S.A.",
      "nombre": "Monetarios",
      "nombreCorto": "Monetarios",
      "descripcion": "",
      "validaMontos": "",
      "minimoRequiereAutorizacion": "",
      "maximoRequiereAutorizacion": "",
      "correlativoImpreso": 301,
      "enviarHost": "",
      "cicloVida": "Activo",
      "validoDesde": "01/02/26",
      "validoHasta": "",
      "totalMonitoreado": "",
      "rutinaCalculamontoConciliar": "",
      "rutinacalculaMontoConciliado": "",
      "esControlEfectivo": "No Aplica"
    },
    {
      "codigo": 302,
      "arbolRaiz": "Byte S.A.",
      "nombre": "Pago de cheques",
      "nombreCorto": "Pago de cheques",
      "descripcion": "",
      "validaMontos": "",
      "minimoRequiereAutorizacion": "",
      "maximoRequiereAutorizacion": "",
      "correlativoImpreso": 302,
      "enviarHost": "",
      "cicloVida": "Activo",
      "validoDesde": "01/02/26",
      "validoHasta": "",
      "totalMonitoreado": "true",
      "rutinaCalculamontoConciliar": "",
      "rutinacalculaMontoConciliado": "",
      "esControlEfectivo": "No Aplica"
    },
    {
      "codigo": 303,
      "arbolRaiz": "Byte S.A.",
      "nombre": "Pago de cheques en ventanilla",
      "nombreCorto": "Pago de cheques e",
      "descripcion": "",
      "validaMontos": "",
      "minimoRequiereAutorizacion": "",
      "maximoRequiereAutorizacion": "",
      "correlativoImpreso": 303,
      "enviarHost": "",
      "cicloVida": "Activo",
      "validoDesde": "01/02/26",
      "validoHasta": "",
      "totalMonitoreado": "",
      "rutinaCalculamontoConciliar": "",
      "rutinacalculaMontoConciliado": "",
      "esControlEfectivo": "No Aplica"
    },
    {
      "codigo": 340,
      "arbolRaiz": "Byte S.A.",
      "nombre": "Ahorros",
      "nombreCorto": "Ahorros",
      "descripcion": "",
      "validaMontos": "",
      "minimoRequiereAutorizacion": "",
      "maximoRequiereAutorizacion": "",
      "correlativoImpreso": 340,
      "enviarHost": "",
      "cicloVida": "Activo",
      "validoDesde": "01/02/26",
      "validoHasta": "",
      "totalMonitoreado": "",
      "rutinaCalculamontoConciliar": "",
      "rutinacalculaMontoConciliado": "",
      "esControlEfectivo": "No Aplica"
    },
    {
      "codigo": 341,
      "arbolRaiz": "Byte S.A.",
      "nombre": "Retiros de ahorro",
      "nombreCorto": "Retiros de ahorro",
      "descripcion": "",
      "validaMontos": "",
      "minimoRequiereAutorizacion": "",
      "maximoRequiereAutorizacion": "",
      "correlativoImpreso": 341,
      "enviarHost": "",
      "cicloVida": "Activo",
      "validoDesde": "01/02/26",
      "validoHasta": "",
      "totalMonitoreado": "true",
      "rutinaCalculamontoConciliar": "",
      "rutinacalculaMontoConciliado": "",
      "esControlEfectivo": "No Aplica"
    },
    {
      "codigo": 342,
      "arbolRaiz": "Byte S.A.",
      "nombre": "Retiros de ahorro con libreta",
      "nombreCorto": "Retiros ahorro C/L",
      "descripcion": "",
      "validaMontos": "",
      "minimoRequiereAutorizacion": "",
      "maximoRequiereAutorizacion": "",
      "correlativoImpreso": 342,
      "enviarHost": "",
      "cicloVida": "Activo",
      "validoDesde": "01/02/26",
      "validoHasta": "",
      "totalMonitoreado": "true",
      "rutinaCalculamontoConciliar": "",
      "rutinacalculaMontoConciliado": "",
      "esControlEfectivo": "No Aplica"
    },
    {
      "codigo": 343,
      "arbolRaiz": "Byte S.A.",
      "nombre": "Retiros de ahorro sin libreta",
      "nombreCorto": "Retiros ahorro S/L",
      "descripcion": "",
      "validaMontos": "",
      "minimoRequiereAutorizacion": "",
      "maximoRequiereAutorizacion": "",
      "correlativoImpreso": 343,
      "enviarHost": "",
      "cicloVida": "Activo",
      "validoDesde": "01/02/26",
      "validoHasta": "",
      "totalMonitoreado": "true",
      "rutinaCalculamontoConciliar": "",
      "rutinacalculaMontoConciliado": "",
      "esControlEfectivo": "No Aplica"
    },
    {
      "codigo": 424,
      "arbolRaiz": "Byte S.A.",
      "nombre": "Cheques de o/b recibidos (saliente)",
      "nombreCorto": "Cheques de o/b reci",
      "descripcion": "",
      "validaMontos": "",
      "minimoRequiereAutorizacion": "",
      "maximoRequiereAutorizacion": "",
      "correlativoImpreso": 424,
      "enviarHost": "",
      "cicloVida": "Activo",
      "validoDesde": "01/02/26",
      "validoHasta": "",
      "totalMonitoreado": "",
      "rutinaCalculamontoConciliar": "",
      "rutinacalculaMontoConciliado": "",
      "esControlEfectivo": "No Aplica"
    }
  ]
}